{
  "Experience": [
    {
      "company": "MageHost",
      "title": "DevOps Engineer - Intern",
      "location": "Delhi",
      "years": "April 2019 - Present"
    },
    {
      "company": "Kirana",
      "title": "Web Development Intern",
      "years": "Oct 2018 - Dec 2018"
    },
    {
      "company": "Speech Markers Pvt. Ltd.",
      "title": "Data Collection And Validation",
      "location": "Pune",
      "years": "Jan 2018"
    }, 
    {
      "company": "Shaastra Automation LLP",
      "title": "Content Development",
      "location": "Gwalior",
      "years": "Aug 2017 - Nov 2017"
    }, 
    {
      "company": "R.I.C.E. Computers",
      "title": "Software Testing",
      "location": "Indore",
      "years": "May 2015 - Jun 2015"
    }  
  ],
  "Education": [
    {
      "Level": "Integrated M.Tech in Information Technology",
      "Insti": "IIIT Gwalior",
      "Passing": "2017-2022",
      "Percentage": "7.3 CGPA (Should it matter?)"
    },
    {
      "Level": "Class 12th",
      "Passing": "2016",
      "Insti": "St. Paul's Convent Sr. Sec. School",
      "Percentage": "91%"
    },
    {
      "Level": "Class 10th",
      "Passing": "2014",
      "Insti": "St. Paul's Convent Sr. Sec. School",
      "Percentage": "80%"
    }
  ],
  "Tech stack": [
    {
      "Skill": "Frontend",
      "Frameworks": "React.js/ Angularjs"
    },
    {
      "Skill": "Backend",
      "Frameworks": "Node.js, GraphQl, Firebase, Flask"
    },
    {
      "Skill": "Databases",
      "Frameworks": "MongoDB, Firebase, Sql"
    },
    {
      "Skill": "Ops",
      "Frameworks": "Lalala"
    }
  ],
  "Achievments": [
    {
      "name": "Lol",
      "description": "Just Kidding"
    }
  ],
  "Projects": [
    {
      "name": "Test",
      "link": "mmm.com",
      "description": "Woah"
    }
  ],
  "Public profiles": [
    {
      "name": "Personal Website",
      "link": "https://ojaswa.me"
    },
    {
      "name": "Github",
      "link": "https://github.com/ojaswa1942"
    },
    {
      "name": "LinkedIn",
      "link": "https://www.linkedin.com/in/ojaswa23/"
    },
    {
      "name": "NPM",
      "link": "https://www.npmjs.com/settings/ojaswa1942/packages"
    },
    {
      "name": "Email",
      "link": "ojaswa1942@gmail.com"
    }
  ]
}